{
  "id": "specflux-staging-env",
  "name": "SpecFlux - Staging",
  "values": [
    {
      "key": "baseUrl",
      "value": "https://specflux-backend-400514527718.us-west1.run.app/api",
      "type": "default",
      "enabled": true
    },
    {
      "key": "firebaseApiKey",
      "value": "",
      "type": "secret",
      "enabled": true,
      "description": "Firebase Web API Key (from Firebase Console > Project Settings)"
    },
    {
      "key": "apiKey",
      "value": "",
      "type": "secret",
      "enabled": true,
      "description": "SpecFlux API key (sfx_...) - preferred auth method"
    },
    {
      "key": "testEmail",
      "value": "dev@specflux.staging",
      "type": "default",
      "enabled": true
    },
    {
      "key": "testPassword",
      "value": "devpass123",
      "type": "default",
      "enabled": true
    },
    {
      "key": "authToken",
      "value": "",
      "type": "secret",
      "enabled": true,
      "description": "Firebase ID token - populated by auth requests"
    },
    {
      "key": "refreshToken",
      "value": "",
      "type": "secret",
      "enabled": true
    },
    {
      "key": "userRef",
      "value": "",
      "type": "default",
      "enabled": true
    },
    {
      "key": "projectRef",
      "value": "",
      "type": "default",
      "enabled": true
    },
    {
      "key": "prdRef",
      "value": "",
      "type": "default",
      "enabled": true
    },
    {
      "key": "prdDocId",
      "value": "",
      "type": "default",
      "enabled": true
    },
    {
      "key": "epicRef",
      "value": "",
      "type": "default",
      "enabled": true
    },
    {
      "key": "taskRef",
      "value": "",
      "type": "default",
      "enabled": true
    },
    {
      "key": "releaseRef",
      "value": "",
      "type": "default",
      "enabled": true
    },
    {
      "key": "criteriaId",
      "value": "",
      "type": "default",
      "enabled": true
    },
    {
      "key": "apiKeyId",
      "value": "",
      "type": "default",
      "enabled": true
    }
  ],
  "_postman_variable_scope": "environment"
}
