{"kind":"identitytoolkit#DownloadAccountResponse","users":[{"localId":"XH2zX5CCrH46kg379cazL44dXS4r","lastLoginAt":"1764687890954","displayName":"test","photoUrl":"","emailVerified":false,"email":"czl0909@gmail.com","salt":"fakeSalt1ktPKlRY88DN0dSMgBKo","passwordHash":"fakeHash:salt=fakeSalt1ktPKlRY88DN0dSMgBKo:password=123456","passwordUpdatedAt":1764687890954,"validSince":"1764687890","mfaInfo":[],"createdAt":"1764687890954","providerUserInfo":[{"providerId":"password","email":"czl0909@gmail.com","federatedId":"czl0909@gmail.com","rawId":"czl0909@gmail.com","displayName":"test","photoUrl":""}]}]}